type_lens/__init__.py
type_lens/__metadata__.py
type_lens/callable_view.py
type_lens/exc.py
type_lens/parameter_view.py
type_lens/py.typed
type_lens/type_view.py
type_lens/typing.py
type_lens/utils.py
type_lens/types/__init__.py
type_lens/types/builtins.py
type_lens/types/empty.py
type_lens-0.2.6.dist-info/METADATA
type_lens-0.2.6.dist-info/WHEEL
type_lens-0.2.6.dist-info/licenses/LICENSE
type_lens-0.2.6.dist-info/RECORD
