Metadata-Version: 2.4
Name: type-lens
Version: 0.2.6
Summary: type-lens is a Python template project designed to simplify the setup of a new project.
Project-URL: Issue Tracker, https://github.com/litestar-org/type-lens/issues?q=is%3Aissue+is%3Aopen+sort%3Aupdated-desc
Project-URL: Changelog, https://github.com/litestar-org/type-lens/releases/
Project-URL: Discord, https://discord.gg/litestar
Project-URL: Blog, https://blog.litestar.dev
Project-URL: homepage, https://litestar.dev/
Project-URL: repository, https://github.com/litestar-org/type-lens
Project-URL: documentation, https://docs.type-lens.litestar.dev/
Author-email: Peter Schutt <peter.github@proton.me>
Maintainer-email: Litestar Developers <hello@litestar.dev>, Cody Fincher <cody@litestar.dev>, Jacob Coffee <jacob@litestar.dev>, Janek Nouvertné <provinzkraut@litestar.dev>, Peter Schutt <peter@litestar.dev>, Visakh Unnikrishnan <guacs@litestar.dev>, Alc <alc@litestar.dev>, Dan Cardin <ddcardin@gmail.com>
License: MIT
License-File: LICENSE
Keywords: developer,litestar-org,programming,tools,type-lens
Classifier: Development Status :: 3 - Alpha
Classifier: Environment :: Web Environment
Classifier: Intended Audience :: Developers
Classifier: License :: OSI Approved :: MIT License
Classifier: Natural Language :: English
Classifier: Operating System :: OS Independent
Classifier: Programming Language :: Python
Classifier: Programming Language :: Python :: 3.8
Classifier: Programming Language :: Python :: 3.9
Classifier: Programming Language :: Python :: 3.10
Classifier: Programming Language :: Python :: 3.11
Classifier: Programming Language :: Python :: 3.12
Classifier: Programming Language :: Python :: 3.13
Classifier: Topic :: Internet :: WWW/HTTP
Classifier: Topic :: Software Development
Classifier: Typing :: Typed
Requires-Python: <4.0,>=3.8
Requires-Dist: eval-type-backport; python_version < '3.10'
Requires-Dist: typing-extensions>=4.1.0
